<?xml version="1.0" encoding="utf-8" ?>
<dwsync>
<file name="_about.scss" server="C:/Users/max_f/Documents/Server/" local="132614922482598993" remote="132614922480000000" Dst="0" />
<file name="_button.scss" server="C:/Users/max_f/Documents/Server/" local="132614922482608982" remote="132614922480000000" Dst="0" />
<file name="_contacts.scss" server="C:/Users/max_f/Documents/Server/" local="132614922482618936" remote="132614922480000000" Dst="0" />
<file name="_experience.scss" server="C:/Users/max_f/Documents/Server/" local="132614922482618936" remote="132614922480000000" Dst="0" />
<file name="_media.scss" server="C:/Users/max_f/Documents/Server/" local="132614922482628914" remote="132614922480000000" Dst="0" />
<file name="_menu.scss" server="C:/Users/max_f/Documents/Server/" local="132614933893648971" remote="132614933890000000" Dst="0" />
<file name="_modal.scss" server="C:/Users/max_f/Documents/Server/" local="132614922482638894" remote="132614922480000000" Dst="0" />
<file name="_portfolio.scss" server="C:/Users/max_f/Documents/Server/" local="132614922482648876" remote="132614922480000000" Dst="0" />
<file name="_prices.scss" server="C:/Users/max_f/Documents/Server/" local="132614922482658836" remote="132614922480000000" Dst="0" />
<file name="_promo.scss" server="C:/Users/max_f/Documents/Server/" local="132615776222402798" remote="132615776220000000" Dst="0" />
<file name="_sidepanel.scss" server="C:/Users/max_f/Documents/Server/" local="132614922482668809" remote="132614922480000000" Dst="0" />
<file name="_skills.scss" server="C:/Users/max_f/Documents/Server/" local="132614922482678795" remote="132614922480000000" Dst="0" />
</dwsync>