<?xml version="1.0" encoding="utf-8" ?>
<dwsync>
<file name="css3.svg" server="C:/Users/max_f/Documents/Server/" local="132615730918114997" remote="132615730910000000" Dst="0" />
<file name="html5.svg" server="C:/Users/max_f/Documents/Server/" local="132615730918134941" remote="132615730910000000" Dst="0" />
<file name="iconfinder_react_1296845.svg" server="C:/Users/max_f/Documents/Server/" local="132614922481455125" remote="132614922480000000" Dst="0" />
<file name="jquery.svg" server="C:/Users/max_f/Documents/Server/" local="132615730918154889" remote="132615730910000000" Dst="0" />
<file name="js.svg" server="C:/Users/max_f/Documents/Server/" local="132615730918164863" remote="132615730910000000" Dst="0" />
<file name="mongo.db.svg" server="C:/Users/max_f/Documents/Server/" local="132615730918174834" remote="132615730910000000" Dst="0" />
<file name="node.js.svg" server="C:/Users/max_f/Documents/Server/" local="132615730918184807" remote="132615730910000000" Dst="0" />
<file name="react.svg" server="C:/Users/max_f/Documents/Server/" local="132615730918194789" remote="132615730910000000" Dst="0" />
</dwsync>